pypevol/__init__.py
pypevol/__main__.py
pypevol/analyzer.py
pypevol/cli.py
pypevol/fetcher.py
pypevol/models.py
pypevol/parser.py
pypevol/reports.py
pypevol/utils.py
pypevol-0.2.2.dist-info/licenses/LICENSE
tests/__init__.py
tests/test_analyzer.py
tests/test_models.py
pypevol-0.2.2.dist-info/METADATA
pypevol-0.2.2.dist-info/WHEEL
pypevol-0.2.2.dist-info/entry_points.txt
pypevol-0.2.2.dist-info/top_level.txt
pypevol-0.2.2.dist-info/RECORD
